tccloud/__init__.py
tccloud/client.py
tccloud/config.py
tccloud/exceptions.py
tccloud/http_client.py
tccloud/models.py
tccloud/utils.py
tccloud-0.4.1.dist-info/LICENSE
tccloud-0.4.1.dist-info/WHEEL
tccloud-0.4.1.dist-info/METADATA
tccloud-0.4.1.dist-info/RECORD
