Metadata-Version: 2.1
Name: tccloud
Version: 0.4.1
Summary: TeraChem Cloud python client. Scalable compute, easy to learn, fast to code.
Home-page: https://github.com/coltonbh/terachem-cloud-pyclient
Author: Colton Hicks
Author-email: pypi@coltonhicks.com
Requires-Python: >=3.7
Classifier: Intended Audience :: Science/Research
Classifier: Operating System :: OS Independent
Classifier: Programming Language :: Python :: 3
Classifier: Programming Language :: Python
Classifier: Programming Language :: Python :: 3 :: Only
Classifier: Programming Language :: Python :: 3.6
Classifier: Programming Language :: Python :: 3.7
Classifier: Programming Language :: Python :: 3.8
Classifier: Programming Language :: Python :: 3.9
Classifier: Topic :: Software Development :: Libraries :: Python Modules
Classifier: Topic :: Software Development :: Libraries
Classifier: Topic :: Software Development
Classifier: Typing :: Typed
Classifier: License :: OSI Approved :: MIT License
Requires-Dist: qcelemental >= 0.24.0
Requires-Dist: httpx >= 0.16.1
Requires-Dist: toml >= 0.10.2
Requires-Dist: flake8 >=3.8.4 ; extra == "dev"
Requires-Dist: pre-commit >= 2.9.3 ; extra == "dev"
Requires-Dist: mypy >=0.942 ; extra == "dev"
Requires-Dist: black >=20.8b1,<21.0b0 ; extra == "dev"
Requires-Dist: isort >=5.7.0,<6.0.0 ; extra == "dev"
Requires-Dist: autoflake >= 1.4 ; extra == "dev"
Requires-Dist: types-toml >= 0.1.1 ; extra == "dev"
Requires-Dist: mkdocs >= 1.1.2 ; extra == "doc"
Requires-Dist: mkdocs-material >= 7.0.3 ; extra == "doc"
Requires-Dist: mkdocstrings >= 0.15.0 ; extra == "doc"
Requires-Dist: markdown-include >= 0.6.0 ; extra == "doc"
Requires-Dist: livereload >=2.6.3 ; extra == "doc"
Requires-Dist: pytest >=6.2.1 ; extra == "test"
Requires-Dist: pytest-cov >=2.10.1,<3.0.0 ; extra == "test"
Requires-Dist: pytest-httpx >=0.10.1 ; extra == "test"
Requires-Dist: pytest-mock >=3.5.1 ; extra == "test"
Requires-Dist: coverage >=5.3.1,<6.0 ; extra == "test"
Project-URL: Documentation, https://mtzgroup.github.io/tccloud/
Provides-Extra: dev
Provides-Extra: doc
Provides-Extra: test
